{
    "wallpaper": "/home/daroch/Pictures/wallpaper/2020_YAM_YZF1000R1SPL_EU_BWM2_STA_001-70560.jpg",
    "alpha": "100",
    "special": {
        "background": "#0a090c",
        "foreground": "#cdcac8",
        "cursor": "#cdcac8"
    },
    "colors": {
        "color0": "#0a090c",
        "color1": "#7D826E",
        "color2": "#949871",
        "color3": "#D2B258",
        "color4": "#525F9A",
        "color5": "#938E8C",
        "color6": "#ABAC8E",
        "color7": "#cdcac8",
        "color8": "#8f8d8c",
        "color9": "#7D826E",
        "color10": "#949871",
        "color11": "#D2B258",
        "color12": "#525F9A",
        "color13": "#938E8C",
        "color14": "#ABAC8E",
        "color15": "#cdcac8"
    }
}